mediafire/__init__.py
mediafire/api.py
mediafire/client.py
mediafire/subsetio.py
mediafire/uploader.py
mediafire/media/__init__.py
mediafire/media/conversion_server_client.py
mediafire-0.6.1.dist-info/LICENSE.txt
mediafire-0.6.1.dist-info/METADATA
mediafire-0.6.1.dist-info/WHEEL
mediafire-0.6.1.dist-info/top_level.txt
mediafire-0.6.1.dist-info/RECORD
