Metadata-Version: 1.1
Name: mediafire
Version: 0.6.1
Summary: Python MediaFire client library
Home-page: UNKNOWN
Author: Roman Yepishev
Author-email: rye@keypressure.com
License: BSD
Keywords: mediafire cloud files sdk storage api upload
Platform: UNKNOWN
Classifier: Development Status :: 3 - Alpha
Classifier: Intended Audience :: Developers
Classifier: Programming Language :: Python :: 2
Classifier: Programming Language :: Python :: 2.7
Classifier: Programming Language :: Python :: 3
Classifier: Programming Language :: Python :: 3.4
Classifier: License :: OSI Approved :: BSD License
